README
setup.py
django_supergeneric.egg-info/PKG-INFO
django_supergeneric.egg-info/SOURCES.txt
django_supergeneric.egg-info/dependency_links.txt
django_supergeneric.egg-info/requires.txt
django_supergeneric.egg-info/top_level.txt
supergeneric/__init__.py
supergeneric/models.py
supergeneric/views.py