Metadata-Version: 1.0
Name: django-supergeneric
Version: 1.0
Summary: django-supergeneric is a small utility library that provides generic aggregator for five most used generic views for any model
Home-page: https://github.com/lig/django-supergeneric
Author: Serge Matveenko
Author-email: s@matveenko.ru
License: UNKNOWN
Platform: UNKNOWN
